README.md
setup.cfg
setup.py
blueshift/__init__.py
blueshift/blueshift.py
blueshift.egg-info/PKG-INFO
blueshift.egg-info/SOURCES.txt
blueshift.egg-info/dependency_links.txt
blueshift.egg-info/top_level.txt