Metadata-Version: 2.1
Name: blueshift
Version: 0.0.1
Summary: Quickly create large amounts of unique serial numbers.
Home-page: https://github.com/mckkaleb/blueshift
Author: Kaleb McKinney
License: UNKNOWN
Download-URL: https://github.com/mckkaleb/blueshift/archive/0.0.1.tar.gz
Platform: UNKNOWN
Classifier: Development Status :: 4 - Beta
Requires-Python: >=3.4
